herokuify_scrapyd/__init__.py
herokuify_scrapyd/app.py
herokuify_scrapyd-1.0.dist-info/LICENSE
herokuify_scrapyd-1.0.dist-info/METADATA
herokuify_scrapyd-1.0.dist-info/WHEEL
herokuify_scrapyd-1.0.dist-info/top_level.txt
herokuify_scrapyd-1.0.dist-info/RECORD
