Metadata-Version: 2.1
Name: herokuify-scrapyd
Version: 1.0
Summary: A package to deploy scrapy spiders to Heroku
Home-page: https://github.com/pypa/sampleproject
Author: Ahmed Rafik Djerah
Author-email: djerahahmedrafik@mail.com
License: UNKNOWN
Platform: UNKNOWN
Classifier: Programming Language :: Python :: 3
Classifier: License :: OSI Approved :: MIT License
Classifier: Operating System :: OS Independent
